{
  "ID": 5912246897350997000,
  "ACTION_TYPE": "SIMCARD_EXT_REF_UPDATE",
  "PARTY_ID": 7980144496541471000,
  "PARTY_NAME": "CLYISwVYyRDg",
  "DUE_DATE": "1601347441015",
  "CREATOR_ID": 399811773095279940,
  "CREATOR_USERNAME": "USER_952",
  "CREATED": "1598221642881",
  "STATUS": "TERMINATED",
  "STARTED": "1590804578739",
  "ENDED": "1593573732657",
  "TRANSITION_NAME": "_suspendre",
  "LIMITED_VISIBILITY": 9,
  "NB_FAILED_UA": 1004157313,
  "NB_SENT_DUAL_FAILED_UA": 4776587907,
  "NB_PENDING_UA": 172504170,
  "NB_COMPLETED_UA": 8775193679,
  "NB_TARGET_ACTIONS": 23978445,
  "OFFER_NAME": null,
  "CUSTOMER_ACCOUNT_CODE": null,
  "NEW_CUSTOMER_ACCOUNT_CODE": "WvdlUxACkl",
  "BYTEL_PREACTIVATION_CODE": null,
  "CUSTOM_FIELD1": null,
  "CUSTOM_FIELD2": "e3(X#OTJRcIl96",
  "CUSTOM_FIELD3": null,
  "CUSTOM_FIELD4": null,
  "CUSTOM_FIELD5": null,
  "CUSTOM_FIELD6": null,
  "PARTY_ID_SRC": 4,
  "PARTY_NAME_SRC": null,
  "PARTY_ID_DEST": 12,
  "PARTY_NAME_DEST": null,
  "ALARM_EXTRA_INFO": null,
  "SMS_MSG": null,
  "SMS_SHORT_CODE": null,
  "SERVICES": "lkPAsKpWDvpvBnWkODZdEzoSFqPpibgAbgQZgiFsLJlxxgkQZzwXiT",
  "APNS": "IZBnN0Hsd8N8)NAHfL!@EB&d5VJmB%GIdb"
}